README.md
pyproject.toml
setup.py
pygments_pasp/__init__.py
pygments_pasp/pasp.py
pygments_pasp.egg-info/PKG-INFO
pygments_pasp.egg-info/SOURCES.txt
pygments_pasp.egg-info/dependency_links.txt
pygments_pasp.egg-info/entry_points.txt
pygments_pasp.egg-info/requires.txt
pygments_pasp.egg-info/top_level.txt