Metadata-Version: 2.1
Name: pygments-pasp
Version: 0.0.4
Summary: Pygments package for pasp
Author-email: Renato Lui Geh <renatogeh@gmail.com>
License: MIT
Project-URL: Repository, https://github.com/RenatoGeh/pygments_pasp
Project-URL: Issues, https://github.com/RenatoGeh/pygments_pasp/issues
Classifier: Programming Language :: Python :: 3
Classifier: License :: OSI Approved :: MIT License
Classifier: Operating System :: POSIX :: Linux
Classifier: Development Status :: 3 - Alpha
Classifier: Environment :: Console
Requires-Python: >=3.10
Requires-Dist: pygments
